{"team_a": "kingler|kingler||noability|swordsdance,hyperbeam,crabhammer,bodyslam|serious|252,252,252,252,252,252|||||]machamp|machamp||noability|earthquake,lowkick,bodyslam,rockslide|serious|252,252,252,252,252,252|||||]chansey|chansey||noability|softboiled,icebeam,thunderwave,thunderbolt|serious|252,252,252,252,252,252|||||]slowbro|slowbro||noability|amnesia,rest,surf,thunderwave|serious|252,252,252,252,252,252|||||]raichu|raichu||noability|thunderbolt,surf,thunderwave,bodyslam|serious|252,252,252,252,252,252|||||]poliwrath|poliwrath||noability|amnesia,blizzard,hypnosis,psychic|serious|252,252,252,252,252,252|||||", "team_b": "venusaur|venusaur||noability|razorleaf,sleeppowder,swordsdance,hyperbeam|serious|252,252,252,252,252,252|||||]persian|persian||noability|slash,bubblebeam,thunderbolt,hyperbeam|serious|252,252,252,252,252,252|||||]blastoise|blastoise||noability|surf,hydropump,earthquake,blizzard|serious|252,252,252,252,252,252|||||]kabutops|kabutops||noability|swordsdance,hyperbeam,slash,surf|serious|252,252,252,252,252,252|||||]porygon|porygon||noability|recover,thunderwave,icebeam,thunderbolt|serious|252,252,252,252,252,252|||||]zapdos|zapdos||noability|drillpeck,thunderbolt,thunderwave,agility|serious|252,252,252,252,252,252|||||", "result": false, "a_fainted": 6, "b_fainted": 4}